{
  "name": "川崎 空",
  "occupation": "エンジニア",
  "age": "28",
  "sex": "女性",
  "residence": "",
  "birthplace": "",
  "characteristics": {
    "str": 30,
    "con": 30,
    "pow": 70,
    "dex": 70,
    "app": 70,
    "siz": 55,
    "int": 45,
    "edu": 99
  },
  "attribute": {
    "hp": 8,
    "mp": 14,
    "mov": 8,
    "build": 0,
    "db": "+0",
    "san": { "value": 67, "max": 99 },
    "luck": 75
  },
  "skills": [
    { "name": "威圧", "value": 15, "edited": false },
    { "name": "言いくるめ", "value": 5, "edited": false },
    { "name": "医学", "value": 1, "edited": false },
    { "name": "運転（自動車）", "value": 40, "edited": true },
    { "name": "運転（）", "value": 20, "edited": false },
    { "name": "応急手当", "value": 50, "edited": true },
    { "name": "オカルト", "value": 5, "edited": false },
    { "name": "隠密", "value": 20, "edited": false },
    { "name": "回避", "value": 35, "edited": false },
    { "name": "科学（工学）", "value": 50, "edited": true },
    { "name": "科学（物理）", "value": 35, "edited": true },
    { "name": "鍵開け", "value": 1, "edited": false },
    { "name": "鑑定", "value": 5, "edited": false },
    { "name": "機械修理", "value": 91, "edited": true },
    { "name": "聞き耳", "value": 24, "edited": true },
    { "name": "近接戦闘（格闘）", "value": 25, "edited": false },
    { "name": "近接戦闘（）", "value": 0, "edited": false },
    { "name": "クトゥルフ神話", "value": 0, "edited": false },
    { "name": "芸術／製作（製図）", "value": 55, "edited": true },
    { "name": "経理", "value": 5, "edited": false },
    { "name": "考古学", "value": 1, "edited": false },
    { "name": "コンピューター", "value": 5, "edited": false },
    { "name": "サバイバル（）", "value": 10, "edited": false },
    { "name": "自然", "value": 10, "edited": false },
    { "name": "射撃（拳銃）", "value": 20, "edited": false },
    { "name": "射撃（ライフル／ショットガン）", "value": 25, "edited": false },
    { "name": "射撃（）", "value": 0, "edited": false },
    { "name": "重機械操作", "value": 75, "edited": true },
    { "name": "乗馬", "value": 5, "edited": false },
    { "name": "信用", "value": 30, "edited": true },
    { "name": "心理学", "value": 10, "edited": false },
    { "name": "人類学", "value": 1, "edited": false },
    { "name": "水泳", "value": 20, "edited": false },
    { "name": "精神分析", "value": 1, "edited": false },
    { "name": "説得", "value": 10, "edited": false },
    { "name": "操縦（ヘリコプター）", "value": 61, "edited": true },
    { "name": "跳躍", "value": 20, "edited": false },
    { "name": "追跡", "value": 10, "edited": false },
    { "name": "手さばき", "value": 10, "edited": false },
    { "name": "電気修理", "value": 50, "edited": true },
    { "name": "電子工学", "value": 1, "edited": false },
    { "name": "投擲", "value": 20, "edited": false },
    { "name": "登攀", "value": 20, "edited": false },
    { "name": "図書館", "value": 40, "edited": true },
    { "name": "ナビゲート", "value": 10, "edited": false },
    { "name": "変装", "value": 5, "edited": false },
    { "name": "法律", "value": 5, "edited": false },
    { "name": "ほかの言語（英語）", "value": 21, "edited": true },
    { "name": "母国語（日本語）", "value": 99, "edited": false },
    { "name": "魅惑", "value": 15, "edited": false },
    { "name": "目星", "value": 25, "edited": false },
    { "name": "歴史", "value": 5, "edited": false }
  ],
  "possessions": [
    {
      "name": "ランドクルーザー",
      "count": "1",
      "detail": "トヨタ ランドクルーザー300 VX\nアバンギャルドブロンズメタリック"
    },
    {
      "name": "タバコ",
      "count": "3",
      "detail": "メビウス・プレミアムメンソール・オプション・パープル５"
    },
    { "name": "100円ライター", "count": "3", "detail": "" }
  ],
  "weapons": [
    {
      "name": "素手",
      "value": "25",
      "damage": "1D3+DB",
      "range": "",
      "attacks": "",
      "ammo": "",
      "malfunction": ""
    }
  ],
  "credit": { "spendingLevel": "", "cash": "", "assetsDetails": "" },
  "backstory": [
    { "name": "容姿の描写", "entries": [{ "text": "リスカ痕" }] },
    {
      "name": "イデオロギー／信念",
      "entries": [{ "text": "明日できることは明日やる", "keyConnection": true }]
    },
    { "name": "重要な人々", "entries": [] },
    { "name": "意味のある場所", "entries": [{ "text": "ヘリのフライト場" }] },
    { "name": "秘蔵の品", "entries": [] },
    { "name": "特徴", "entries": [] },
    { "name": "負傷、傷跡", "entries": [] },
    { "name": "恐怖症、マニア", "entries": [] },
    { "name": "魔導書、呪文、アーティファクト", "entries": [] },
    { "name": "遭遇した超自然の存在", "entries": [] }
  ],
  "fellows": [],
  "note": "航空エンジニア\n休日はドライブかヘリコプターでのフライトを行うのが趣味\nヘビースモーカー\nリスカ痕があるが現在はしていない\n\n3d6*5 STR (3D6*5) ＞ 6[1,4,1]*5 ＞ 30\n3d6*5 CON (3D6*5) ＞ 6[1,4,1]*5 ＞ 30\n3d6*5 POW (3D6*5) ＞ 14[5,3,6]*5 ＞ 70\n3d6*5 DEX (3D6*5) ＞ 14[4,6,4]*5 ＞ 70\n3d6*5 APP(3D6*5) ＞ 14[6,5,3]*5 ＞ 70\n(2d6+6)*5 SIZ  ((2D6+6)*5) ＞ (5[2,3]+6)*5 ＞ 55\n(2d6+6)*5 EDU ((2D6+6)*5) ＞ (12[6,6]+6)*5 ＞ 90\n(2d6+6)*5 INT ((2D6+6)*5) ＞ (3[2,1]+6)*5 ＞ 45\n3d6*5 幸運 (3D6*5) ＞ 15[6,6,3]*5 ＞ 75\n\nCC\u003c=90 (1D100\u003c=90) ボーナス・ペナルティダイス[0] ＞ 99 ＞ 99 ＞ 失敗\n1d10 (1D10) ＞ 9",
  "chatpalette": "CC\u003c={SAN} 正気度ロール\nCC\u003c=75 幸運\nCC\u003c=30 STR\nCC\u003c=30 CON\nCC\u003c=70 POW\nCC\u003c=70 DEX\nCC\u003c=70 APP\nCC\u003c=55 SIZ\nCC\u003c=45 INT\nCC\u003c=45 アイデア\nCC\u003c=99 知識\nCC\u003c=40 運転（自動車）\nCC\u003c=50 応急手当\nCC\u003c=35 回避\nCC\u003c=50 科学（工学）\nCC\u003c=35 科学（物理）\nCC\u003c=91 機械修理\nCC\u003c=24 聞き耳\nCC\u003c=25 近接戦闘（格闘）\nCC\u003c=55 芸術／製作（製図）\nCC\u003c=75 重機械操作\nCC\u003c=30 信用\nCC\u003c=61 操縦（ヘリコプター）\nCC\u003c=50 電気修理\nCC\u003c=40 図書館\nCC\u003c=21 ほかの言語（英語）\nCC\u003c=99 母国語（日本語）\nCC\u003c=25 目星\n1D3+{DB} 素手",
  "portraitURL": "https://object-storage.tyo2.conoha.io/v1/nc_8d0b8b8762ee4050b883be8088ea3a37/charaeno/ycZdyjEWQ4U9xlDU5W_q_?v=lkdIJLICWl"
}
